Soujanya2/addTwoNumbers.py
Soujanya2-1.0.0.dist-info/LICENSE
Soujanya2-1.0.0.dist-info/METADATA
Soujanya2-1.0.0.dist-info/WHEEL
Soujanya2-1.0.0.dist-info/entry_points.txt
Soujanya2-1.0.0.dist-info/top_level.txt
Soujanya2-1.0.0.dist-info/RECORD
