Metadata-Version: 2.1
Name: Soujanya2
Version: 1.0.0
Summary: A Python package to add two numbers.
Home-page: UNKNOWN
Author: Soujany
Author-email: hamsu8977@gmail.com
License: MIT
Platform: UNKNOWN
Classifier: License :: OSI Approved :: MIT License
Classifier: Programming Language :: Python :: 3
Classifier: Programming Language :: Python :: 3.7
Requires-Dist: requests
